pyrcrack/__init__.py
pyrcrack/airbase.py
pyrcrack/aircrack.py
pyrcrack/airdecap.py
pyrcrack/airdecloack.py
pyrcrack/aireplay.py
pyrcrack/airmon.py
pyrcrack/airodump.py
pyrcrack/executor.py
pyrcrack/models.py
pyrcrack-1.2.6.dist-info/METADATA
pyrcrack-1.2.6.dist-info/WHEEL
pyrcrack-1.2.6.dist-info/RECORD
