Metadata-Version: 2.1
Name: pyrcrack
Version: 1.2.6
Summary: Pythonic aircrack-ng bindings
Project-URL: Documentation, https://github.com/XayOn/pyrcrack#readme
Project-URL: Issues, https://github.com/XayOn/pyrcrack/issues
Project-URL: Source, https://github.com/XayOn/pyrcrack
Author-email: David Francos <me@davidfrancos.net>
Classifier: Development Status :: 4 - Beta
Classifier: Programming Language :: Python
Classifier: Programming Language :: Python :: 3.7
Classifier: Programming Language :: Python :: 3.8
Classifier: Programming Language :: Python :: 3.9
Classifier: Programming Language :: Python :: 3.10
Classifier: Programming Language :: Python :: 3.11
Classifier: Programming Language :: Python :: Implementation :: CPython
Classifier: Programming Language :: Python :: Implementation :: PyPy
Requires-Python: >=3.7
Requires-Dist: async-timeout>=3
Requires-Dist: docopt>=0.6
Requires-Dist: dotmap>=1
Requires-Dist: geopy>=2
Requires-Dist: mac-vendor-lookup>=0.1
Requires-Dist: parse>=1.12
Requires-Dist: pyshark>=0.4
Requires-Dist: pytest-asyncio>=0.14
Requires-Dist: rich>=7
Requires-Dist: stringcase>=1
Requires-Dist: xmltodict>=0.12
